{"version":{"pluginId":"default","version":"current","label":"Next","banner":null,"badge":false,"noIndex":false,"className":"docs-version-current","isLast":true,"docsSidebars":{"mainSidebar":[{"type":"link","href":"/smart-home-planner/docs/intro","label":"🏠 Карточка продукта","docId":"intro","unlisted":false},{"type":"category","label":"📋 Требования","items":[{"type":"link","href":"/smart-home-planner/docs/requirements/use-cases","label":"Use Cases","docId":"requirements/use-cases","unlisted":false},{"type":"link","href":"/smart-home-planner/docs/requirements/nfr-fr","label":"FR и NFR","docId":"requirements/nfr-fr","unlisted":false}],"collapsed":true,"collapsible":true},{"type":"category","label":"🗄️ Архитектура","items":[{"type":"link","href":"/smart-home-planner/docs/architecture/erd","label":"ERD (Модель данных)","docId":"architecture/erd","unlisted":false},{"type":"link","href":"/smart-home-planner/docs/architecture/storage","label":"Хранение данных","docId":"architecture/storage","unlisted":false},{"type":"link","href":"/smart-home-planner/docs/architecture/async-api","label":"AsyncAPI (RabbitMQ)","docId":"architecture/async-api","unlisted":false}],"collapsed":true,"collapsible":true},{"type":"category","label":"⚡ API","items":[{"type":"link","href":"/smart-home-planner/docs/api/overview","label":"API Reference","docId":"api/overview","unlisted":false},{"type":"link","href":"/smart-home-planner/docs/api/error-codes","label":"Коды ошибок","docId":"api/error-codes","unlisted":false}],"collapsed":true,"collapsible":true},{"type":"category","label":"🔗 Интеграции","items":[{"type":"link","href":"/smart-home-planner/docs/integrations/sequence-diagrams","label":"Sequence-диаграммы","docId":"integrations/sequence-diagrams","unlisted":false},{"type":"link","href":"/smart-home-planner/docs/integrations/platformization","label":"Платформизация (B2B)","docId":"integrations/platformization","unlisted":false}],"collapsed":true,"collapsible":true}]},"docs":{"api/error-codes":{"id":"api/error-codes","title":"Коды ошибок","description":"Формат ошибки","sidebar":"mainSidebar"},"api/overview":{"id":"api/overview","title":"API Reference","description":"Base URL//api.smartplanner.com/v1","sidebar":"mainSidebar"},"architecture/async-api":{"id":"architecture/async-api","title":"AsyncAPI — RabbitMQ","description":"Проблема и решение","sidebar":"mainSidebar"},"architecture/erd":{"id":"architecture/erd","title":"ERD — Модель данных","description":"Обоснование ключевых решений","sidebar":"mainSidebar"},"architecture/storage":{"id":"architecture/storage","title":"Хранение данных","description":"Сущности, акторы и характер взаимодействия","sidebar":"mainSidebar"},"integrations/platformization":{"id":"integrations/platformization","title":"Платформизация","description":"Замена компонентов на внешние платформы","sidebar":"mainSidebar"},"integrations/sequence-diagrams":{"id":"integrations/sequence-diagrams","title":"Sequence-диаграммы","description":"SD-01 — Регистрация пользователя (UC-01)","sidebar":"mainSidebar"},"intro":{"id":"intro","title":"Карточка продукта","description":"Версия Production · Обновлено: 2025-05-01","sidebar":"mainSidebar"},"requirements/nfr-fr":{"id":"requirements/nfr-fr","title":"FR и NFR","description":"Функциональные требования (FR)","sidebar":"mainSidebar"},"requirements/use-cases":{"id":"requirements/use-cases","title":"Use Cases","description":"UC-01 — Регистрация нового пользователя","sidebar":"mainSidebar"}}}}